easy_selenium/__init__.py
easy_selenium/logger.py
easy_selenium/authentication/__init__.py
easy_selenium/authentication/login/__init__.py
easy_selenium/authentication/login/google.py
easy_selenium/authentication/login/linkedin.py
easy_selenium/common/__init__.py
easy_selenium/common/funcs.py
easy_selenium/cookies/__init__.py
easy_selenium/cookies/cookies.py
easy_selenium/driver/__init__.py
easy_selenium/driver/constants.py
easy_selenium/driver/utils.py
easy_selenium/driver/chrome/__init__.py
easy_selenium/driver/chrome/check.py
easy_selenium/driver/chrome/clean.py
easy_selenium/driver/chrome/download.py
easy_selenium/driver/chrome/driver.py
easy_selenium/driver/firefox/__init__.py
easy_selenium/driver/firefox/check.py
easy_selenium/driver/firefox/download.py
easy_selenium/driver/firefox/driver.py
easy_selenium/screenshots/__init__.py
easy_py_selenium-0.1.5.dist-info/LICENCE
easy_py_selenium-0.1.5.dist-info/METADATA
easy_py_selenium-0.1.5.dist-info/WHEEL
easy_py_selenium-0.1.5.dist-info/top_level.txt
easy_py_selenium-0.1.5.dist-info/RECORD
