Metadata-Version: 2.1
Name: easy-py-selenium
Version: 0.1.5
Summary: A tool that makes working with selenium easier.
Home-page: https://github.com/SelmiAbderrahim/easy-selenium
Author: Selmi Abderrahim
Author-email: contact@selmi.tech
License: MIT
Project-URL: Bug Tracker, https://github.com/SelmiAbderrahim/easy-selenium/issues
Keywords: python automation tools with selenium
Platform: UNKNOWN
Classifier: Development Status :: 3 - Alpha
Classifier: Intended Audience :: Developers
Classifier: Topic :: Software Development :: Build Tools
Classifier: License :: OSI Approved :: MIT License
Classifier: Programming Language :: Python :: 3.7
Classifier: Programming Language :: Python :: 3.8
Classifier: Programming Language :: Python :: 3.9
Classifier: Programming Language :: Python :: 3.10
License-File: LICENCE
Requires-Dist: lucd (==0.1.7)
Requires-Dist: python-decouple (==3.6)
Requires-Dist: loguru (==0.6.0)
